echo_mailer/__init__.py
echo_mailer/main.py
echo_mailer/test.py
echo_mailer-0.0.1.dist-info/LICENSE
echo_mailer-0.0.1.dist-info/METADATA
echo_mailer-0.0.1.dist-info/WHEEL
echo_mailer-0.0.1.dist-info/top_level.txt
echo_mailer-0.0.1.dist-info/RECORD
